dgcli/__init__.py
dgcli-0.0.1.dist-info/DESCRIPTION.rst
dgcli-0.0.1.dist-info/METADATA
dgcli-0.0.1.dist-info/RECORD
dgcli-0.0.1.dist-info/WHEEL
dgcli-0.0.1.dist-info/metadata.json
dgcli-0.0.1.dist-info/top_level.txt
