Metadata-Version: 2.0
Name: dgcli
Version: 0.0.1
Summary: Command Line Interface for Deep Generator
Home-page: UNKNOWN
Author: Deep Generator Inc
Author-email: contact@deepgenerator.com
License: UNKNOWN
Keywords: deepgenerator,cli,deep learning,infrastructure
Platform: UNKNOWN
